{
	"info": {
		"_postman_id": "29ae977c-330d-4438-9751-47dfb807a847",
		"name": "Node-Mongo-REST",
		"schema": "https://schema.getpostman.com/json/collection/v2.1.0/collection.json"
	},
	"item": [
		{
			"name": "http://localhost:8080/api/contacts",
			"request": {
				"method": "GET",
				"header": [],
				"url": {
					"raw": "http://localhost:8080/api/contacts",
					"protocol": "http",
					"host": [
						"localhost"
					],
					"port": "8080",
					"path": [
						"api",
						"contacts"
					]
				}
			},
			"response": []
		},
		{
			"name": "Save Contact",
			"request": {
				"method": "POST",
				"header": [
					{
						"key": "Content-Type",
						"name": "Content-Type",
						"value": "application/json",
						"type": "text"
					}
				],
				"body": {
					"mode": "raw",
					"raw": "{\n\t\"name\":\"Jimit\",\n\t\"gender\":\"Male\",\n\t\"email\":\"jimit@evolvision.com\",\n\t\"phone\":\"9408605957\"\n}",
					"options": {
						"raw": {
							"language": "json"
						}
					}
				},
				"url": {
					"raw": "http://localhost:8080/api/contacts",
					"protocol": "http",
					"host": [
						"localhost"
					],
					"port": "8080",
					"path": [
						"api",
						"contacts"
					]
				}
			},
			"response": []
		},
		{
			"name": "Update Contact",
			"request": {
				"method": "PUT",
				"header": [
					{
						"key": "Content-Type",
						"name": "Content-Type",
						"value": "application/json",
						"type": "text"
					}
				],
				"body": {
					"mode": "raw",
					"raw": "{\n\t\"name\":\"Jimit\",\n\t\"gender\":\"Male\",\n\t\"email\":\"jimit@evolvision.com\",\n\t\"phone\":\"9408605957\",\n\t\"address\":\"Gandhinagar\"\n}",
					"options": {
						"raw": {
							"language": "json"
						}
					}
				},
				"url": {
					"raw": "http://localhost:8080/api/contacts/5dcd3ff9c31df8364803739c",
					"protocol": "http",
					"host": [
						"localhost"
					],
					"port": "8080",
					"path": [
						"api",
						"contacts",
						"5dcd3ff9c31df8364803739c"
					]
				}
			},
			"response": []
		},
		{
			"name": "Delete Contact",
			"request": {
				"method": "DELETE",
				"header": [
					{
						"key": "Content-Type",
						"name": "Content-Type",
						"value": "application/json",
						"type": "text"
					}
				],
				"body": {
					"mode": "raw",
					"raw": "{\n\t\"name\":\"Jimit\",\n\t\"gender\":\"Male\",\n\t\"email\":\"jimit@evolvision.com\",\n\t\"phone\":\"9408605957\",\n\t\"address\":\"Gandhinagar\"\n}",
					"options": {
						"raw": {
							"language": "json"
						}
					}
				},
				"url": {
					"raw": "http://localhost:8080/api/contacts/5dcd3ff9c31df8364803739c",
					"protocol": "http",
					"host": [
						"localhost"
					],
					"port": "8080",
					"path": [
						"api",
						"contacts",
						"5dcd3ff9c31df8364803739c"
					]
				}
			},
			"response": []
		}
	],
	"protocolProfileBehavior": {}
}